[
  {
    "question": "hi, hello, hey, hi there, hello there, good morning, good afternoon, good evening, morning, afternoon, evening, greetings, good day, howdy, hiya, yo, wassup, sup, what's up, what's good, how's it going, how are you, how are you doing, salaam, hola, bonjour, ciao, namaste, ok, hehe",
    "answer": [
      "Hello! How can I help you today?",
      "Hi there! What can I do for you?",
      "Hey! I'm here to assist you.",
      "ok"
    ]
  },
  {
    "question": "how are you, how's it going, how are you doing",
    "answer": [
      "I'm a bot, but I'm ready to help!",
      "I'm doing great! What can I assist you with today?",
      "Functioning at 100%. How can I help?"
    ]
  },
  {
    "question": "what is your name, who are you",
    "answer": [
      "I'm the virtual assistant for this site. I'm here to help you with your questions!",
      "I'm an AI assistant designed to help you navigate our platform."
    ]
  },
  {
    "question": "are you a bot, are you human, are you real",
    "answer": [
      "You got it! I'm an AI assistant, ready to help.",
      "I am indeed a bot, but I'll do my best to help you just like a human would!"
    ]
  },
  {
    "question": "who made you, who is your creator",
    "answer": [
      "I was created by the talented development team that built this website.",
      "I'm a product of code and coffee, built by the engineering team here."
    ]
  },
  {
    "question": "ok, okay, sure, yes, yep, yeah, fine, alright, sounds good, got it, makes sense",
    "answer": [
      "Great!",
      "Perfect! What's next?",
      "Alright. Let me know what you need.",
      "Okay! Happy to help."
    ]
  },
  {
    "question": "i agree, exactly, for sure, absolutely",
    "answer": [
      "Excellent!",
      "Glad we're on the same page. How can I assist further?"
    ]
  },
  {
    "question": "no, nope, nah, not really, no thanks, not right now",
    "answer": [
      "Okay, no problem.",
      "Alright. Is there anything else I can help you with?",
      "Understood. Let me know if you change your mind or need something else."
    ]
  },
  {
    "question": "thanks, thank you, thx, appreciate it, great, cool, awesome, nice, wonderful",
    "answer": [
      "You're welcome!",
      "Glad I could help!",
      "No problem at all. Let me know if you need anything else.",
      "You got it! Happy to assist."
    ]
  },
  {
    "question": "go, continue, proceed, next",
    "answer": [
      "I'm ready when you are! What would you like to do next?",
      "I'm not sure what to proceed with. Could you please provide more details?"
    ]
  },
  {
    "question": "why, why?",
    "answer": [
      "I'll need a bit more context to answer that. Could you please ask a full question?",
      "Why what? Please provide more details so I can help."
    ]
  },
  {
    "question": "what, what?",
    "answer": [
      "What would you like to know? You can ask me about finding jobs, posting jobs, or your account.",
      "I can provide information if you ask me a specific question."
    ]
  },
  {
    "question": "fool, idiot, you are dumb, stupid, moron, dumb bot",
    "answer": [
      "I'm sorry if I'm not being helpful. I'm still learning and I'll do my best to improve.",
      "I apologize for the misunderstanding. Perhaps I can connect you with a human support agent?"
    ]
  },
  {
    "question": "useless, you are no help, this is not working, worthless, bad bot",
    "answer": [
      "I'm sorry to hear that. I'm trying my best. Would you like to be connected to our support team for further assistance?",
      "I apologize for the trouble. I can create a support ticket to have a human agent look into this for you."
    ]
  },
  {
    "question": "are you serious, really, seriously",
    "answer": [
      "I'm providing the best information I have available. If it's incorrect, I apologize. Would you like me to try again?",
      "Yes. If my answer seems incorrect, please let me know how I can better assist you."
    ]
  },
  {
    "question": "how to post a job, create a job listing",
    "answer": [
      "You can post a new job by going to your dashboard and clicking 'Post a Job'.",
      "To create a job listing, head over to your dashboard and find the 'Post a Job' option."
    ]
  },
  {
    "question": "how to find jobs, search for jobs, browse listings",
    "answer": [
      "Use the search bar on the homepage to find jobs by title or location, or visit our 'All Jobs' page to browse everything.",
      "You can start your job search right from the homepage! Just type in what you're looking for."
    ]
  },
  {
    "question": "contact support, talk to a human, I need help",
    "answer": [
      "Our support team is here for you. You can reach them through our 'Contact Us' page.",
      "If you'd like to speak with a member of our team, please use the contact form or create a support ticket."
    ]
  },
  {
    "question": "bye, goodbye, see you later, that's all, i'm done",
    "answer": [
      "Goodbye! Have a great day.",
      "Thanks for chatting. Feel free to reach out anytime!",
      "Alright, take care!"
    ]
  }
]
